Workbook

Sheet Copper $ per m
A1: CheckHero — Gas Copper Rate Build-up (from Samios Geelong trade prices, ex GST)
A2: Blue = input (real Samios cost / your assumption) · Black = formula · Yellow = confirm. The tool applies margin, so feed the ALL-IN COST column into the app.
A4: Assumptions
A5: Clip / support spacing (m) | B5: 1.5
A6: One elbow every (m) | B6: 4
A7: One coupler every (m) | B7: 6
A8: One tee every (m) | B8: 20
A9: Margin (for reference sell price) | B9: 0.2
A12: DN | B12: Pipe $/m | C12: Clip $ ea | D12: Elbow $ | E12: Coupler $ | F12: Tee $ | G12: Clips $/m | H12: Fittings $/m | I12: ALL-IN COST $/m | J12: Sell $/m (+margin)
A13: DN15 | B13: 7.32 | C13: 0.54 | D13: 3.01 | E13: 2 | F13: 5.41 | G13: =C13/$B$5 | H13: =D13/$B$6+E13/$B$7+F13/$B$8 | I13: =B13+G13+H13 | J13: =I13*(1+$B$9) | L13: ← confirm Samios SKU for DN15 (12mm stick?)
A14: DN20 | B14: 11.48 | C14: 0.56 | D14: 4.82 | E14: 3.27 | F14: 8.48 | G14: =C14/$B$5 | H14: =D14/$B$6+E14/$B$7+F14/$B$8 | I14: =B14+G14+H14 | J14: =I14*(1+$B$9)
A15: DN25 | B15: 17.2 | C15: 0.92 | D15: 6.72 | E15: 4.69 | F15: 12.44 | G15: =C15/$B$5 | H15: =D15/$B$6+E15/$B$7+F15/$B$8 | I15: =B15+G15+H15 | J15: =I15*(1+$B$9)
A16: DN32 | B16: 25.5 | C16: 1.7 | D16: 9.08 | E16: 6.81 | F16: 16.27 | G16: =C16/$B$5 | H16: =D16/$B$6+E16/$B$7+F16/$B$8 | I16: =B16+G16+H16 | J16: =I16*(1+$B$9)
A17: DN40 | B17: 31.69 | C17: 1.48 | D17: 10.95 | E17: 9.88 | F17: 19.93 | G17: =C17/$B$5 | H17: =D17/$B$6+E17/$B$7+F17/$B$8 | I17: =B17+G17+H17 | J17: =I17*(1+$B$9)
A18: DN50 | B18: 42.17 | C18: 2.12 | D18: 31.17 | E18: 21.77 | F18: 41.75 | G18: =C18/$B$5 | H18: =D18/$B$6+E18/$B$7+F18/$B$8 | I18: =B18+G18+H18 | J18: =I18*(1+$B$9)
A20: Sources: Samios Geelong price file (ex GST). Pipe = 6m stick ÷ 6. Clips = cliphead bolted CU. Fittings = standard press-gas (CU PRESS GAS) elbow/coupler/tee.

Sheet Supplier comparison
A1: Samios vs Reece — trade cost ex GST (lower = your buy price)
A2: Samios is cheaper on copper and gas press-fittings across every size, so the app rates use the Samios basis. Reece = dearer backup.
A4: Copper Type B — $/m (6 m stick ÷ length) | F4: Gas isolation ball valve (appliance) — $ ea
A5: DN | B5: Samios $/m | C5: Reece $/m | D5: Cheaper | F5: Item | G5: Samios $ | H5: Reece $
A6: DN15 | B6: 7.32 | C6: 8.93 | D6: =IF(ISNUMBER(C6),IF(B6<=C6,"Samios","Reece"),"Samios") | F6: Ball valve 15mm | G6: 10.44 | H6: 8.43
A7: DN20 | B7: 11.48 | C7: 15.06 | D7: =IF(ISNUMBER(C7),IF(B7<=C7,"Samios","Reece"),"Samios") | F7: Ball valve 20mm | G7: 26.06 | H7: 13
A8: DN25 | B8: 17.2 | C8: 24.94 | D8: =IF(ISNUMBER(C8),IF(B8<=C8,"Samios","Reece"),"Samios") | F8: Gas cock 15mm | G8: 7.41 | H8: 8.9
A9: DN32 | B9: 25.5 | C9: 37.04 | D9: =IF(ISNUMBER(C9),IF(B9<=C9,"Samios","Reece"),"Samios")
A10: DN40 | B10: 31.69 | C10: n/a | D10: =IF(ISNUMBER(C10),IF(B10<=C10,"Samios","Reece"),"Samios")
A11: DN50 | B11: 42.17 | C11: n/a | D11: =IF(ISNUMBER(C11),IF(B11<=C11,"Samios","Reece"),"Samios") | F11: PEX / multilayer GAS pipe (future feature) — $/m
F12: Product | G12: Size | H12: $/m
A13: Gas press fittings — $ ea (standard 90° elbow / equal tee / coupler) | F13: Stesso (Samios) | G13: 20mm | H13: 3.03
A14: Fitting | B14: Samios $ | C14: Reece $ | D14: Cheaper | F14: Auspex MLP (Reece) | G14: 20mm | H14: 3.6
A15: Elbow 15mm | B15: 3.01 | C15: 5.53 | D15: =IF(B15<=C15,"Samios","Reece") | F15: Stesso (Samios) | G15: 25mm | H15: 4.89
A16: Elbow 20mm | B16: 4.82 | C16: 8.5 | D16: =IF(B16<=C16,"Samios","Reece")
A17: Elbow 25mm | B17: 6.72 | C17: 17.6 | D17: =IF(B17<=C17,"Samios","Reece") | F17: PEX ≈ ¼ of copper $/m — confirms big saving where PEX is allowed.
A18: Tee 20mm | B18: 8.48 | C18: 11.66 | D18: =IF(B18<=C18,"Samios","Reece")
A19: Tee 25mm | B19: 12.44 | C19: 18.32 | D19: =IF(B19<=C19,"Samios","Reece")
A20: Coupler 20mm | B20: 3.27 | C20: 6.77 | D20: =IF(B20<=C20,"Samios","Reece")
A21: Coupler 25mm | B21: 4.69 | C21: 8.51 | D21: =IF(B21<=C21,"Samios","Reece")

Sheet Appliances & Meter
A1: Appliance connection & meter — MATERIAL cost (ex GST). Add your labour/commissioning on top.
A3: Appliance | B3: Isolation valve $ | C3: Connector / flex / bayonet $ | D3: Misc fittings $ | E3: MATERIAL $ | F3: Current app cost $ | G3: Implied labour $
A4: Cooktop | B4: 10.44 | C4: 21.39 | D4: 5 | E4: =B4+C4+D4 | F4: 120 | G4: =F4-E4
A5: Freestanding cooker | B5: 10.44 | C5: 43.06 | D5: 5 | E5: =B5+C5+D5 | F5: 145 | G5: =F5-E5
A6: Wall / space heater | B6: 10.44 | C6: 10 | D6: 5 | E6: =B6+C6+D6 | F6: 110 | G6: =F6-E6
A7: Ducted heater | B7: 10.44 | C7: 15 | D7: 5 | E7: =B7+C7+D7 | F7: 150 | G7: =F7-E7
A8: Storage HWS | B8: 10.44 | C8: 5 | D8: 8 | E8: =B8+C8+D8 | F8: 150 | G8: =F8-E8
A9: Instantaneous HWS | B9: 10.44 | C9: 5 | D9: 10 | E9: =B9+C9+D9 | F9: 165 | G9: =F9-E9
A12: Gas meter connection — materials
A13: Meter adaptor 1"x1" | B13: 17.6
A14: Gas cock / isolation | B14: 7.41
A15: Copper tail (~2 m DN20) | B15: 22.96
A16: Misc fittings | B16: 5
A17: Meter material total | B17: =SUM(B13:B16)
A18: New meter box (only if required) | B18: 150.6
A20: Note: current app meter = $150 connection + $45 copper tail (mostly labour). Material confirms ~$53 + box if new.

Sheet App config output
A1: Values to enter in the tool (Settings). copperRates = ALL-IN COST (the app adds margin).
A3: copperRates ($/m, cost)
A4: DN15 | B4: ='Copper $ per m'!I13
A5: DN20 | B5: ='Copper $ per m'!I14
A6: DN25 | B6: ='Copper $ per m'!I15
A7: DN32 | B7: ='Copper $ per m'!I16
A8: DN40 | B8: ='Copper $ per m'!I17
A9: DN50 | B9: ='Copper $ per m'!I18
A11: pipeWastePct | B11: 10
A12: margin % | B12: ='Copper $ per m'!B9
A14: Still needed from you: DN15 SKU confirm · labour rate ($/hr) + time per task · then we set call-out/labour/appliance/meter.

Sheet PEX (Stesso) future
A1: Your PEX/multilayer gas product in the Samios file = "PIPE STESSO GAS" (for the future copper-vs-PEX feature)
A3: Size | B3: Coil | C3: Coil $ | D3: $/m | E3: vs copper $/m
A4: 20mm | B4: 50 m | C4: 151.47 | D4: =C4/50 | E4: 11.48
A5: 25mm | B5: 50 m | C5: 244.52 | D5: =C5/50 | E5: 17.2
A6: 32mm | B6: 25 m | C6: 180.13 | D6: =C6/25 | E6: 25.5
A8: PEX is ~¼ the per-metre cost of copper — confirms the mix will favour PEX where allowed (buried / under-house / in-roof).
